TrigDroid_Infrastructure/__init__.py
TrigDroid_Infrastructure/application/__init__.py
TrigDroid_Infrastructure/application/orchestrator.py
TrigDroid_Infrastructure/infrastructure/__init__.py
TrigDroid_Infrastructure/infrastructure/android.py
TrigDroid_Infrastructure/infrastructure/configuration.py
TrigDroid_Infrastructure/infrastructure/dependency_injection.py
TrigDroid_Infrastructure/infrastructure/logging.py
TrigDroid_Infrastructure/interfaces/__init__.py
TrigDroid_Infrastructure/test_runners/__init__.py
TrigDroid_Infrastructure/test_runners/frida_test_runner.py
TrigDroid_Infrastructure/test_runners/sensor_test_runner.py
TrigDroid_Infrastructure/test_runners/test_context.py
trigdroid/__init__.py
trigdroid/_version.py
trigdroid/exceptions.py
trigdroid/api/__init__.py
trigdroid/api/bypass_config.py
trigdroid/api/config.py
trigdroid/api/devices.py
trigdroid/api/main.py
trigdroid/api/quick_start.py
trigdroid/api/results.py
trigdroid/api/runners.py
trigdroid/cli/__init__.py
trigdroid/cli/main.py
trigdroid/core/__init__.py
trigdroid/core/cleanup.py
trigdroid/core/enums.py
trigdroid/scripts/__init__.py
trigdroid/scripts/main.js
trigdroid/scripts/main_bundle.js
trigdroid/scripts/trigdroid_bypass_bundle.js
trigdroid/scripts/trigdroid_bypass_rpc.js
trigdroid/scripts/types.js
trigdroid/scripts/utils.js
trigdroid/scripts/hooks/android-build.js
trigdroid/scripts/hooks/android-sensors.js
trigdroid/scripts/hooks/debug-detection.js
trigdroid/scripts/hooks/emulator-detection.js
trigdroid/scripts/hooks/frida-detection.js
trigdroid/scripts/hooks/root-detection.js
trigdroid/scripts/hooks/ssl-unpinning.js
trigdroid-2.0.6.dist-info/METADATA
trigdroid-2.0.6.dist-info/WHEEL
trigdroid-2.0.6.dist-info/entry_points.txt
trigdroid-2.0.6.dist-info/licenses/LICENSE
trigdroid-2.0.6.dist-info/RECORD
