Metadata-Version: 2.4
Name: trigdroid
Version: 2.0.6
Summary: Android Sandbox Payload Trigger Framework for Security Research
Project-URL: Homepage, https://github.com/fkie-cad/Sandroid_TrigDroid
Project-URL: Documentation, https://fkie-cad/Sandroid_TrigDroid
Project-URL: Repository, https://github.com/fkie-cad/Sandroid_TrigDroid.git
Project-URL: Bug Tracker, https://github.com/fkie-cad/Sandroid_TrigDroid/issues
Project-URL: Changelog, https://github.com/fkie-cad/Sandroid_TrigDroid/blob/main/CHANGELOG.md
Author-email: Daniel Baier <daniel.baier@fkie.fraunhofer.de>, Simon Hüsch <simon.huesch@smail.inf.h-brs.de>
Maintainer-email: Daniel Baier <daniel.baier@fkie.fraunhofer.de>
License: MIT License
License-File: LICENSE
Keywords: android,frida,malware-analysis,mobile-security,penetration-testing,reverse-engineering,security
Classifier: Development Status :: 4 - Beta
Classifier: Environment :: Console
Classifier: Environment :: Other Environment
Classifier: Intended Audience :: Developers
Classifier: Intended Audience :: Science/Research
Classifier: Intended Audience :: System Administrators
Classifier: License :: OSI Approved :: MIT License
Classifier: Natural Language :: English
Classifier: Operating System :: MacOS
Classifier: Operating System :: POSIX :: Linux
Classifier: Programming Language :: JavaScript
Classifier: Programming Language :: Python :: 3
Classifier: Programming Language :: Python :: 3.9
Classifier: Programming Language :: Python :: 3.10
Classifier: Programming Language :: Python :: 3.11
Classifier: Programming Language :: Python :: 3.12
Classifier: Topic :: Security
Classifier: Topic :: Software Development :: Testing
Classifier: Topic :: System :: Systems Administration
Classifier: Topic :: Utilities
Classifier: Typing :: Typed
Requires-Python: >=3.9
Requires-Dist: click>=8.1.0
Requires-Dist: colorama>=0.4.6
Requires-Dist: pydantic>=2.0.0
Requires-Dist: pyyaml>=6.0
Requires-Dist: requests>=2.31.0
Requires-Dist: rich>=13.0.0
Requires-Dist: termcolor>=2.3.0
Provides-Extra: dev
Requires-Dist: black>=23.0.0; extra == 'dev'
Requires-Dist: isort>=5.12.0; extra == 'dev'
Requires-Dist: mypy>=1.0.0; extra == 'dev'
Requires-Dist: pre-commit>=3.0.0; extra == 'dev'
Requires-Dist: pylint>=2.17.0; extra == 'dev'
Requires-Dist: pytest-asyncio>=0.21.0; extra == 'dev'
Requires-Dist: pytest-cov>=4.0.0; extra == 'dev'
Requires-Dist: pytest-mock>=3.10.0; extra == 'dev'
Requires-Dist: pytest>=7.0.0; extra == 'dev'
Requires-Dist: types-pyyaml>=6.0.0; extra == 'dev'
Requires-Dist: types-requests>=2.31.0; extra == 'dev'
Provides-Extra: docs
Requires-Dist: markdown-it-py>=3.0.0; extra == 'docs'
Requires-Dist: mdit-py-plugins>=0.4.0; extra == 'docs'
Requires-Dist: myst-parser>=2.0.0; extra == 'docs'
Requires-Dist: sphinx-autobuild>=2021.3.14; extra == 'docs'
Requires-Dist: sphinx-autodoc-typehints>=1.24.0; extra == 'docs'
Requires-Dist: sphinx-copybutton>=0.5.0; extra == 'docs'
Requires-Dist: sphinx-rtd-theme>=2.0.0; extra == 'docs'
Requires-Dist: sphinx>=7.0.0; extra == 'docs'
Provides-Extra: frida
Requires-Dist: frida-tools>=12.0.0; extra == 'frida'
Requires-Dist: frida>=16.0.0; extra == 'frida'
Provides-Extra: full
Requires-Dist: appium-python-client>=3.0.0; extra == 'full'
Requires-Dist: frida-tools>=12.0.0; extra == 'full'
Requires-Dist: frida>=16.0.0; extra == 'full'
Requires-Dist: numpy>=1.24.0; extra == 'full'
Requires-Dist: pillow>=9.0.0; extra == 'full'
Requires-Dist: selenium>=4.0.0; extra == 'full'
Provides-Extra: lint
Requires-Dist: black>=23.0.0; extra == 'lint'
Requires-Dist: isort>=5.12.0; extra == 'lint'
Requires-Dist: mypy>=1.0.0; extra == 'lint'
Requires-Dist: pylint>=2.17.0; extra == 'lint'
Requires-Dist: ruff>=0.1.0; extra == 'lint'
Provides-Extra: test
Requires-Dist: coverage[toml]>=7.0.0; extra == 'test'
Requires-Dist: pytest-asyncio>=0.21.0; extra == 'test'
Requires-Dist: pytest-cov>=4.0.0; extra == 'test'
Requires-Dist: pytest-mock>=3.10.0; extra == 'test'
Requires-Dist: pytest>=7.0.0; extra == 'test'
